flowercare_exporter/__init__.py
flowercare_exporter/graphite.py
flowercare_exporter/main.py
flowercare_exporter/prometheus.py
flowercare_exporter-0.3.1.dist-info/entry_points.txt
flowercare_exporter-0.3.1.dist-info/LICENSE
flowercare_exporter-0.3.1.dist-info/WHEEL
flowercare_exporter-0.3.1.dist-info/METADATA
flowercare_exporter-0.3.1.dist-info/RECORD
