Metadata-Version: 2.3
Name: flowercare_exporter
Version: 0.3.1
Summary: Export Miflora Bluetooth LE sensor to Graphite and Prometheus
Author-email: Jürgen Hötzel <juergen@hoetzel.info>
Classifier: License :: OSI Approved :: MIT License
Requires-Dist: PyGObject >= 3.50.0
Requires-Dist: pyright ; extra == "dev"
Requires-Dist: ruff ; extra == "dev"
Requires-Dist: PyGObject-stubs ; extra == "dev"
Project-URL: Home, https://github.com/juergenhoetzel/flowercare_exporter
Provides-Extra: dev
